voxe/__init__.py
voxe/protocol.py
voxe-0.0.3.dist-info/METADATA
voxe-0.0.3.dist-info/WHEEL
voxe-0.0.3.dist-info/top_level.txt
voxe-0.0.3.dist-info/RECORD
