Metadata-Version: 2.1
Name: voxe
Version: 0.0.3
Summary: A simple transport layer protocol
Home-page: https://github.com/aiyojun/pysolv
Author: aiyojun
Author-email: aiyojun@gmail.com
Classifier: Programming Language :: Python :: 3
Requires-Python: >=3.0
